README.rst
setup.py
cyrax/__init__.py
cyrax/autoreload.py
cyrax/conf.py
cyrax/core.py
cyrax/events.py
cyrax/models.py
cyrax/rstpost.py
cyrax/server.py
cyrax/utils.py
cyrax.egg-info/PKG-INFO
cyrax.egg-info/SOURCES.txt
cyrax.egg-info/dependency_links.txt
cyrax.egg-info/entry_points.txt
cyrax.egg-info/requires.txt
cyrax.egg-info/top_level.txt
cyrax/template/__init__.py
cyrax/template/rstextensions.py
cyrax/template/templatefilters.py
cyrax/template/templatefunctions.py
cyrax/template/templatetags.py
cyrax/template/typogrify.py