Metadata-Version: 1.1
Name: cyrax
Version: 2.6
Summary: Static site generator
Home-page: http://piranha.org.ua/cyrax/
Author: Alexander Solovyov
Author-email: alexander@solovyov.net
License: ISC
Platform: any
Classifier: Environment :: Console
Classifier: License :: OSI Approved :: ISC License (ISCL)
Classifier: Operating System :: OS Independent
Classifier: Programming Language :: Python
Classifier: Topic :: Internet :: WWW/HTTP
Classifier: Topic :: Utilities
